elasticcsv/__init__.py
elasticcsv/csv2es.py
elasticcsv/elastic_csv.py
elasticcsv/elastic_wrapper.py
elasticcsv-0.4.1.dist-info/licenses/LICENSE.txt
elasticcsv-0.4.1.dist-info/METADATA
elasticcsv-0.4.1.dist-info/WHEEL
elasticcsv-0.4.1.dist-info/entry_points.txt
elasticcsv-0.4.1.dist-info/top_level.txt
elasticcsv-0.4.1.dist-info/RECORD
