Metadata-Version: 2.4
Name: elasticcsv
Version: 0.4.1
Summary: elasticsearch csv upload download utility
Home-page: 
Author: juguerre
Author-email: "J. Andres Guerrero" <juguerre@gmail.com>
License: MIT License
Requires-Python: >=3.9
License-File: LICENSE.txt
Requires-Dist: elasticsearch>=8.17.1
Requires-Dist: pandas>=2.2.3
Requires-Dist: python-box>=7.3.2
Requires-Dist: pytz>=2025.1
Requires-Dist: pyyaml>=6.0.2
Requires-Dist: requests>=2.32.3
Requires-Dist: toolz>=1.0.0
Requires-Dist: tqdm>=4.67.1
Requires-Dist: typer>=0.15.2
Requires-Dist: yarl>=1.18.3
Dynamic: author
Dynamic: license-file
Dynamic: requires-python
